latticegeometrylib/CellConfiguration.py
latticegeometrylib/Generator.py
latticegeometrylib/Geometry.py
latticegeometrylib/Lattice.py
latticegeometrylib/Miscellaneous.py
latticegeometrylib/UnitaryCell.py
latticegeometrylib/__init__.py
latticegeometrylib-0.0.19.dist-info/METADATA
latticegeometrylib-0.0.19.dist-info/WHEEL
latticegeometrylib-0.0.19.dist-info/top_level.txt
latticegeometrylib-0.0.19.dist-info/RECORD
